Workbook

Sheet Assumptions
A1: Data monetization: illustrative 3-year revenue model (ALL INPUTS ARE ASSUMPTIONS, blue = editable)
A3: Scenario (1=Low, 2=Base, 3=High) | B3: 2
A4: Customer multiplier | B4: =CHOOSE(B3,0.6,1,1.4)
A5: Annual price uplift after Y1 | B5: 0.05
A7: Stream | B7: Customers Y1 | C7: Customers Y2 | D7: Customers Y3 | E7: ARPA Y1 (USD/yr) | F7: Gross margin | G7: Pricing logic
A8: Insights reports (subscription) | B8: 8 | C8: 20 | D8: 40 | E8: 6000 | F8: 0.85 | G8: Annual subscription by category bundle
A9: Data API (tiered) | B9: 5 | C9: 15 | D9: 35 | E9: 12000 | F9: 0.8 | G9: Tiered by calls + history depth
A10: Audience segments (activation) | B10: 4 | C10: 10 | D10: 18 | E10: 30000 | F10: 0.6 | G10: CPM-style / rev share with activation partner
A11: Data licensing / partnerships | B11: 1 | C11: 3 | D11: 5 | E11: 80000 | F11: 0.85 | G11: Annual contract, aggregated datasets only
A13: Team and run cost (USD/yr)
A14: Item | B14: Y1 | C14: Y2 | D14: Y3
A15: Product, data science, engineering (FTE-equivalent) | B15: 420000 | C15: 520000 | D15: 600000
A16: Legal, security, compliance | B16: 60000 | C16: 70000 | D16: 80000
A17: GTM and partnerships | B17: 80000 | C17: 120000 | D17: 160000

Sheet Model
A1: Revenue, gross profit and payback (USD)
A3: Revenue | B3: Y1 | C3: Y2 | D3: Y3
A4: =Assumptions!A8 | B4: =Assumptions!B8*Assumptions!$B$4*Assumptions!E8 | C4: =Assumptions!C8*Assumptions!$B$4*Assumptions!E8*(1+Assumptions!$B$5) | D4: =Assumptions!D8*Assumptions!$B$4*Assumptions!E8*(1+Assumptions!$B$5)^2
A5: =Assumptions!A9 | B5: =Assumptions!B9*Assumptions!$B$4*Assumptions!E9 | C5: =Assumptions!C9*Assumptions!$B$4*Assumptions!E9*(1+Assumptions!$B$5) | D5: =Assumptions!D9*Assumptions!$B$4*Assumptions!E9*(1+Assumptions!$B$5)^2
A6: =Assumptions!A10 | B6: =Assumptions!B10*Assumptions!$B$4*Assumptions!E10 | C6: =Assumptions!C10*Assumptions!$B$4*Assumptions!E10*(1+Assumptions!$B$5) | D6: =Assumptions!D10*Assumptions!$B$4*Assumptions!E10*(1+Assumptions!$B$5)^2
A7: =Assumptions!A11 | B7: =Assumptions!B11*Assumptions!$B$4*Assumptions!E11 | C7: =Assumptions!C11*Assumptions!$B$4*Assumptions!E11*(1+Assumptions!$B$5) | D7: =Assumptions!D11*Assumptions!$B$4*Assumptions!E11*(1+Assumptions!$B$5)^2
A8: Total revenue | B8: =SUM(B4:B7) | C8: =SUM(C4:C7) | D8: =SUM(D4:D7)
A10: Gross profit | B10: Y1 | C10: Y2 | D10: Y3
A11: =Assumptions!A8 | B11: =B4*Assumptions!$F$8 | C11: =C4*Assumptions!$F$8 | D11: =D4*Assumptions!$F$8
A12: =Assumptions!A9 | B12: =B5*Assumptions!$F$9 | C12: =C5*Assumptions!$F$9 | D12: =D5*Assumptions!$F$9
A13: =Assumptions!A10 | B13: =B6*Assumptions!$F$10 | C13: =C6*Assumptions!$F$10 | D13: =D6*Assumptions!$F$10
A14: =Assumptions!A11 | B14: =B7*Assumptions!$F$11 | C14: =C7*Assumptions!$F$11 | D14: =D7*Assumptions!$F$11
A15: Total gross profit | B15: =SUM(B11:B14) | C15: =SUM(C11:C14) | D15: =SUM(D11:D14)
A17: Total team and run cost | B17: =SUM(Assumptions!B15:B17) | C17: =SUM(Assumptions!C15:C17) | D17: =SUM(Assumptions!D15:D17)
A18: Operating contribution | B18: =B15-B17 | C18: =C15-C17 | D18: =D15-D17
A19: Cumulative contribution | B19: =B18 | C19: =B19+C18 | D19: =C19+D18
A21: Revenue mix Y3: top stream share | B21: =MAX(D4:D7)/D8
A22: Break-even year (cumulative >= 0) | B22: =IF(B19>=0,"Y1",IF(C19>=0,"Y2",IF(D19>=0,"Y3","After Y3")))

Sheet Scenarios
A1: Scenario comparison (static values of the Model for each multiplier, computed with formulas)
A3: Scenario | B3: Multiplier | C3: Y3 revenue | D3: Y3 contribution
A4: Low | B4: 0.6 | C4: =Model!D8/Assumptions!$B$4*B4 | D4: =Model!D15/Assumptions!$B$4*B4-Model!D17
A5: Base | B5: 1 | C5: =Model!D8/Assumptions!$B$4*B5 | D5: =Model!D15/Assumptions!$B$4*B5-Model!D17
A6: High | B6: 1.4 | C6: =Model!D8/Assumptions!$B$4*B6 | D6: =Model!D15/Assumptions!$B$4*B6-Model!D17
A8: Note: contribution scales with the multiplier because costs are held fixed; that is the point of the exercise (operating leverage).
